{
  "_name": "strongholdCrossing",
  "min": 1,
  "max": 5,
  "loot": [
    {
      "weight": 10,
      "id": "minecraft:iron_ingot",
      "damage": 0,
      "min": 1,
      "max": 5
    },
    {
      "weight": 5,
      "id": "minecraft:gold_ingot",
      "damage": 0,
      "min": 1,
      "max": 3
    },
    {
      "weight": 5,
      "id": "minecraft:redstone",
      "damage": 0,
      "min": 4,
      "max": 9
    },
    {
      "weight": 10,
      "id": "minecraft:coal",
      "damage": 0,
      "min": 3,
      "max": 8
    },
    {
      "weight": 15,
      "id": "minecraft:bread",
      "damage": 0,
      "min": 1,
      "max": 3
    },
    {
      "weight": 15,
      "id": "minecraft:apple",
      "damage": 0,
      "min": 1,
      "max": 3
    },
    {
      "weight": 1,
      "id": "minecraft:iron_pickaxe",
      "damage": 0,
      "min": 1,
      "max": 1
    },
    {
      "weight": 1,
      "id": "minecraft:enchanted_book",
      "damage": 0,
      "min": 1,
      "max": 1
    },
    {
      "weight": 25,
      "id": "BiomesOPlenty:flowers",
      "damage": 3,
      "min": 1,
      "max": 4
    },
    {
      "weight": 25,
      "id": "BiomesOPlenty:flowers",
      "damage": 2,
      "min": 1,
      "max": 4
    },
    {
      "weight": 6,
      "id": "arcticmobs:palesoup",
      "damage": 0,
      "min": 1,
      "max": 6
    },
    {
      "weight": 4,
      "id": "arcticmobs:frostboltscepter",
      "damage": 0,
      "min": 1,
      "max": 1
    },
    {
      "weight": 4,
      "id": "arcticmobs:frostwebscepter",
      "damage": 0,
      "min": 1,
      "max": 1
    },
    {
      "weight": 4,
      "id": "arcticmobs:tundrascepter",
      "damage": 0,
      "min": 1,
      "max": 1
    },
    {
      "weight": 4,
      "id": "arcticmobs:icefirescepter",
      "damage": 0,
      "min": 1,
      "max": 1
    },
    {
      "weight": 4,
      "id": "arcticmobs:blizzardscepter",
      "damage": 0,
      "min": 1,
      "max": 1
    },
    {
      "weight": 6,
      "id": "demonmobs:devillasagna",
      "damage": 0,
      "min": 1,
      "max": 6
    },
    {
      "weight": 4,
      "id": "demonmobs:doomfirescepter",
      "damage": 0,
      "min": 1,
      "max": 1
    },
    {
      "weight": 4,
      "id": "demonmobs:hellfirescepter",
      "damage": 0,
      "min": 1,
      "max": 1
    },
    {
      "weight": 4,
      "id": "demonmobs:devilstarscepter",
      "damage": 0,
      "min": 1,
      "max": 1
    },
    {
      "weight": 4,
      "id": "demonmobs:demoniclightningscepter",
      "damage": 0,
      "min": 1,
      "max": 1
    },
    {
      "weight": 6,
      "id": "desertmobs:ambercake",
      "damage": 0,
      "min": 1,
      "max": 6
    },
    {
      "weight": 4,
      "id": "desertmobs:scythescepter",
      "damage": 0,
      "min": 1,
      "max": 1
    },
    {
      "weight": 4,
      "id": "desertmobs:mudshotscepter",
      "damage": 0,
      "min": 1,
      "max": 1
    },
    {
      "weight": 6,
      "id": "forestmobs:paleosalad",
      "damage": 0,
      "min": 1,
      "max": 6
    },
    {
      "weight": 4,
      "id": "forestmobs:lifedrainscepter",
      "damage": 0,
      "min": 1,
      "max": 1
    },
    {
      "weight": 6,
      "id": "freshwatermobs:lapisfishandchips",
      "damage": 0,
      "min": 1,
      "max": 6
    },
    {
      "weight": 4,
      "id": "freshwatermobs:aquapulsescepter",
      "damage": 0,
      "min": 1,
      "max": 1
    },
    {
      "weight": 6,
      "id": "infernomobs:searingtaco",
      "damage": 0,
      "min": 1,
      "max": 6
    },
    {
      "weight": 4,
      "id": "infernomobs:emberscepter",
      "damage": 0,
      "min": 1,
      "max": 1
    },
    {
      "weight": 4,
      "id": "infernomobs:cinderfallsword",
      "damage": 0,
      "min": 1,
      "max": 1
    },
    {
      "weight": 4,
      "id": "infernomobs:magmascepter",
      "damage": 0,
      "min": 1,
      "max": 1
    },
    {
      "weight": 4,
      "id": "infernomobs:scorchfirescepter",
      "damage": 0,
      "min": 1,
      "max": 1
    },
    {
      "weight": 6,
      "id": "junglemobs:tropicalcurry",
      "damage": 0,
      "min": 1,
      "max": 6
    },
    {
      "weight": 4,
      "id": "junglemobs:poopscepter",
      "damage": 0,
      "min": 1,
      "max": 1
    },
    {
      "weight": 4,
      "id": "mountainmobs:boulderblastscepter",
      "damage": 0,
      "min": 1,
      "max": 1
    },
    {
      "weight": 4,
      "id": "mountainmobs:arcanelaserstormscepter",
      "damage": 0,
      "min": 1,
      "max": 1
    },
    {
      "weight": 6,
      "id": "mountainmobs:peakskebab",
      "damage": 0,
      "min": 1,
      "max": 6
    },
    {
      "weight": 6,
      "id": "plainsmobs:bulwarkburger",
      "damage": 0,
      "min": 1,
      "max": 6
    },
    {
      "weight": 6,
      "id": "saltwatermobs:seashellmaki",
      "damage": 0,
      "min": 1,
      "max": 6
    },
    {
      "weight": 4,
      "id": "shadowmobs:spectralboltscepter",
      "damage": 0,
      "min": 1,
      "max": 1
    },
    {
      "weight": 4,
      "id": "shadowmobs:bloodleechscepter",
      "damage": 0,
      "min": 1,
      "max": 1
    },
    {
      "weight": 6,
      "id": "shadowmobs:bloodchili",
      "damage": 0,
      "min": 1,
      "max": 6
    },
    {
      "weight": 6,
      "id": "swampmobs:mosspie",
      "damage": 0,
      "min": 1,
      "max": 6
    },
    {
      "weight": 4,
      "id": "swampmobs:poisonrayscepter",
      "damage": 0,
      "min": 1,
      "max": 1
    },
    {
      "weight": 4,
      "id": "swampmobs:venomshotscepter",
      "damage": 0,
      "min": 1,
      "max": 1
    },
    {
      "weight": 4,
      "id": "swampmobs:venomaxeblade",
      "damage": 0,
      "min": 1,
      "max": 1
    },
    {
      "weight": 1,
      "id": "HardcoreEnderExpansion:temple_caller",
      "damage": 0,
      "min": 0,
      "max": 1
    },
    {
      "keep": "chylex.hee.world.loot.WeightedRandomKnowledgeNote",
      "id": "HardcoreEnderExpansion:knowledge_note",
      "damage": 0,
      "nbt": false,
      "count": 1
    },
    {
      "weight": 3,
      "id": "ExtraUtilities:divisionSigil",
      "damage": 0,
      "min": 1,
      "max": 1
    }
  ]
}